{
    "displayText": "black",
    "stage": "ViVi",
    "name": "Viian Wong Jia Xi",
    "reveal": "February 14, 2017 ",
    "debut": "April 17, 2017",
    "bday": "December 9, 1996 ",
    "bplace": "Hong Kong",
    "bloodGrp": "B",

    "traineeDuration": "?",
    "nextGirlImg": "--",
    "img": "https://i.imgur.com/LqYpnc5.jpg",
    "sign": "https://vignette.wikia.nocookie.net/loonatheworld/images/4/44/ViVi_signature.png",

    "memNo": "Fifth",
    "animal": "🦌",
    "color": {
        "name": "Light Pink",
        "hex": "#FF94B0",
        "rgb": "rgb(255, 148, 176)"
    },
    "given": "Wong Kahei, Hwang A-ra, BB cream (비비 크림)",

    "hashtags": "#MyWay",
    "teamPostion": "Matnae (eldest, but similar to 'Maknae')",
    "charmPoint": "Being expressive, A mindset that always takes on challenges.",

    "playlist": "- thank u, next - Ariana Grande<br>- Ciao Adios - Anne-Marie",
    "goals": "LOOΠΔ being successful, LOOΠΔ being happy, Having a concert in Hong Kong",

    "msgToOrbit": "It has been a year since I met Orbits. Of course, we've spent more than a year together. Thank you for being with us all the time. I'm always happy and thankful. You know this is just the beginning, right!? Let's always be together. My beloved Orbits ♥︎ “Orbit Loona”",

    "mv": [
        { "record": ["2017", "Love&Live", "Love & Live", "Main", "4K4b9Z9lSwc"] },
        { "record": ["2017", "You and Me Together (Special MV)", "Love & Live", "Main", "2_r4kDUzslg"] },
        
        { "record": ["2017", "Everyday I Love You (feat. HaSeul)", "ViVi", "Main", "ZNcBZM5SvbY"] },
        { "record": ["2017", "Everyday I Need You (feat. JinSoul)", "ViVi", "Main", "yphYFDJ4J4w"] },
        
        { "record": ["2017", "Sonatine", "Love & Evil", "Main", "a6JmCdDs_GM"] },
        { "record": ["2017", "Rain 51db", "Love & Evil", "Main", "GhcY79E7am0"] },
        
        { "record": ["2017", "new", "Yves", "Cameo", "LIDe-yTxda0"] },
        { "record": ["2017", "The Carol 2.0", "The Carol 2.0", "Main", "_5N16N_T23k"] },

        { "record": ["2018", "favOriTe", "[++]", "Main", "AFJPFfnzZ7w"] },
        { "record": ["2018", "Hi High", "[++]", "Main", "846cjX0ZTrk"] },
        { "record": ["2018", "Butterfly", "[xx]", "Main", "XEOCbFJjRw0"] }
    ],

    "wd": [
        { "record": ["2017", "Do You Remember The First Time We Met?", "ViVi (Herself)", "https://www.youtube.com/playlist?list=PLgUyA0NDuB-1HiLwm-aC2HEOQ-zMtCCCX"] },
        { "record": ["2017", "Do You Remember The First Time We Met? Season 2", "ViVi (Herself)", "https://www.youtube.com/playlist?list=PLgUyA0NDuB-0E8fbbHbOm3kmAK96Y7qGR"] }
    ]
}