{
            "id": 80,
            "contentId": "ep80",
            "videoId": "HgmFd_JKTkA",
            "title": "이달의소녀탐구 #80 (LOONA TV #80)",
            "date": "March 15, 2017",
            "era": " LOOΠΔ ⅓\n",
            "members": " ViVi, HaSeul, HyunJin, HeeJin\n",
            "blurred": " Probably staffers.\n",
            "songs": " Love & Live\n",
            "location": " Incheon, Flight\n",
            "summary": "They are on their way to New Zealand.<br>0:22 -- A random foreigner approaches HaSeul and all the girls start crushing over him.<br> (He seems interested in HaSeul only)<br>They depart for New Zealand.        ",
            "views": 116171,
            "likes": 4146,
            "comments": 181
        }