{
            "id": 445,
            "contentId": "ep445",
            "videoId": "nIU1_n9Chd0",
            "title": "이달의소녀탐구 #445 (LOONA TV #445)",
            "date": "November 22, 2018",
            "era": " LOONAbirth\n",
            "members": " LOOΠΔ\n",
            "blurred": " --\n",
            "songs": " Stylish, Perfect Love\n",
            "location": " Debut Concert - LOOΠΔBirth Location\n",
            "summary": "0:01 -- ⅓ is back after their group performance. The next song is 'Stylish'.<br>0:08 -- Kim Lip and JinSoul harmonize Stylish backstage.<br>0:30 -- After the performance, the rest have prepared a special event for HaSeul's birthday and the birthday song starts playing. HaSeul is touched and thanks everyone.<br>0:47 -- The group performs 'Perfect Love' and the episode ends.        ",
            "views": 46311,
            "likes": 5240,
            "comments": 274
        }