{
            "id": 27,
            "contentId": "ep27",
            "videoId": "7OiacQpSR7o",
            "title": "이달의소녀탐구 #27 (LOONA TV #27)",
            "date": "November 24, 2016",
            "era": " HyunJin Solo\n",
            "members": " HyunJin\n",
            "blurred": " -- \n",
            "songs": " I’ll Be There\n",
            "location": " Japan\n",
            "summary": "0:14 -- HyunJin: “In Summer~ Ice Green Tea~”.<br>0:17 -- Drinks strawberry milk and acts as if she is shooting a commercial.\t",
            "views": 110506,
            "likes": 3329,
            "comments": 45
        }