{
            "id": 288,
            "contentId": "ep288",
            "videoId": "JDGnPcE9tQc",
            "title": "이달의소녀탐구 #288 (LOOΠΔ TV #288)",
            "date": "March 7, 2018",
            "era": " LOONA Pre-Debut\n",
            "members": " HyunJin, HeeJin, YeoJin, HaSeul\n",
            "blurred": " --\n",
            "songs": " Into The New Heart, Valentine Girl\n",
            "location": " Cinematic Theory Teaser Shoot Location\n",
            "summary": "0:18 -- HeeJin: “Hello, we’re 3Jin and we are pretty.” HyunJin does ugly face here<br>0:36 -- The actors, HyunSeul unite and discuss about Womanna. They have a small<br> quarrel. \t",
            "views": 82401,
            "likes": 4764,
            "comments": 306
        }