{
            "id": 131,
            "contentId": "ep131",
            "videoId": "fZx9bsIb-v4",
            "title": "이달의소녀탐구 #131 (LOONA TV #131)",
            "date": "June 5, 2017",
            "era": " Kim Lip Solo\n",
            "members": " Kim Lip\n",
            "blurred": " --\n",
            "songs": " Eclipse\n",
            "location": " Photostudio #3\n",
            "summary": "The episode starts off Lip looking gorgeous (as always).<br>0:09 -- The photoshoot for Lip’s single album ends and she blows off a candle.<br>Then we see a flashback of her photoshoot journey.<br>0:31 -- She mentions about her training period and how she is glad that the her debut is <br> close.\t",
            "views": 82183,
            "likes": 2917,
            "comments": 111
        }