{
            "id": 101,
            "contentId": "ep101",
            "videoId": "dG5aBUHGnXM",
            "title": "이달의소녀탐구 #101 (LOONA TV #101)",
            "date": "April 25, 2017",
            "era": " ViVi Solo\n",
            "members": " ViVi, HaSeul\n",
            "blurred": "\n",
            "songs": " Everyday I Love You\n",
            "location": " ??\n",
            "summary": "It’s the beginning of the ViVi era!<br>0:03 -- ViVi waving hello (this is a freakin’ adorable wave).<br>0:07 -- ViVi checks her watch. ViVi is not wearing a watch. “It’s three thirty”<br>0:17 -- “It’s Like Train to Busan!” ViVi describes her love of zombies! <br>0:27 -- “I’m a fan of zombies” This is just a really cute declaration of love for murderous <br> people-eating monsters.<br>0:34 -- HaSeul declares that going to Busan is going to a foreign country for ViVi. The joke <br> totally flops.<br>0:46 -- The world’s weakest “hwaiting!” with HaSeul and ViVi        ",
            "views": 77417,
            "likes": 2660,
            "comments": 90
        }