{
            "id": 404,
            "contentId": "ep404",
            "videoId": "kTaiO27oXic",
            "title": "이달의소녀탐구 #404 (LOONA TV #404)",
            "date": "September 27, 2018",
            "era": " [++]\n",
            "members": " HaSeul, HeeJin, HyunJin, YeoJin, ViVi, Kim Lip, JinSoul, Choerry,\n",
            "blurred": "--",
            "songs": " Girl Front\n",
            "location": " favOriTe MV Teaser Shoot Location",
            "summary": "HaSeul PD visits all the members of LOOΠΔ one- by-one<br>0:18 -- While referring to YeoJin: “Number 4, kid?”. YeoJin: “What kid?”<br>0:24 -- While referring to Kim Lip: “Oh you look sexy~”<br>0:44 -- HaSeul looks for Go Won but she went to fix her make up.<br> *drum rolls (YeoJin style): dugugugu*<br>0:51 -- HaSeul: “Number 12!”. Olivia Hye: “End Number!”<br>I guess we won’t need the ‘Blurred Girls’ section anymore.\t",
            "views": 64909,
            "likes": 6285,
            "comments": 231
        }