{
            "id": 147,
            "contentId": "ep147",
            "videoId": "VA6CmHOoFek",
            "title": "이달의소녀탐구 #147 (LOONA TV #147)",
            "date": "July 1, 2017",
            "era": " JinSoul Solo\n",
            "members": " JinSoul, Kim Lip\n",
            "blurred": " (Unknown?)\n",
            "songs": " SInging In The Rain\n",
            "location": " Photoshoot Site #1\n",
            "summary": "0:21 -- JinSoul: “I’m representing the color blue and it is completely opposite to Kim Lip’s”<br>0:36: “I recorded it so well. Blue~”<br>0:40 -- KimSoul then ponder over what color will the next member represent.<br>They head off to the next shooting site.\t",
            "views": 89712,
            "likes": 2884,
            "comments": 171
        }