{
            "id": 190,
            "contentId": "ep190",
            "videoId": "RHBziGG6KR8",
            "title": "이달의소녀탐구 #190 (LOONA TV #190)",
            "date": "October 10, 2017",
            "era": " ODD EYE CIRCLE\n",
            "members": " Choerry, JinSoul, Kim Lip\n",
            "blurred": "--",
            "songs": " Girl Front\n",
            "location": " Desert, LA\n",
            "summary": "0:07 -- It is windy and it is messing up JinSoul’s hair.<br>0:21 -- LipRry do a wavy dance in the wind.<br>0:30 -- The wind is making it hard for them to see but they still have the photoshoot.    ",
            "views": 77084,
            "likes": 2884,
            "comments": 123
        }